qdpxlib/__init__.py
qdpxlib/qdpxlib.py
qdpxlib-0.1.4.dist-info/LICENSE
qdpxlib-0.1.4.dist-info/METADATA
qdpxlib-0.1.4.dist-info/WHEEL
qdpxlib-0.1.4.dist-info/top_level.txt
qdpxlib-0.1.4.dist-info/RECORD
