Metadata-Version: 2.1
Name: qdpxlib
Version: 0.1.4
Summary: Python API for easy handling (importing and exporting) of QDPX (MAXQDA) files.
Home-page: https://github.com/oriyonay/aqc
Author: Ori Yonay, Anwesha Basu, Carlos Morales, Texas A&M Center for Teaching Excellence
Author-email: Ori Yonay <oyonay12@tamu.edu>, Anwesha Basu <anwesha.basu@tamu.edu>
Project-URL: Homepage, https://github.com/oriyonay/aqc
Project-URL: Issues, https://github.com/oriyonay/aqc/issues
Classifier: Programming Language :: Python :: 3
Classifier: License :: OSI Approved :: MIT License
Classifier: Operating System :: OS Independent
Requires-Python: >=3.6
License-File: LICENSE
